Workbook

Sheet Read me
A1: Uber vs Ola vs Rapido: what riders complain about
A2: Pranav Thatavarti · real Google Play reviews, India, English · pulled 2026-10-20
A4: What this is
A5: I pulled every English review from the India Play Store for Uber, Ola and Rapido posted between 20 Jul and 19 Oct 2026. That's 80,548 reviews.
A6: I took a random sample of 3,000 per app and had an LLM tag each one with one primary theme from a fixed list of 15. Then I checked 50 random tags by hand.
A8: Tabs
A9: Summary: app IDs, pull date, review counts and star split for the full 3-month pull.
A10: Theme pivot: count and share of each theme per app. These are live COUNTIFS on the Reviews tab, so if you re-tag a row the pivot moves.
A11: Quotes: real reviews for each app's top 3 complaints. Phone numbers, UPI IDs and plates are masked. No reviewer names.
A12: Validation: 50 random tags. I labelled them myself without seeing the model's tag, then compared.
A13: Themes: the definition of each theme, as given to the model.
A14: Reviews: all 9,000 tagged reviews. Filter by app or theme. The printed view shows the first rows only.
... A21: Model: Claude Sonnet, one call per 40 reviews, fixed theme list. One post-rule: 'safe ride' style praise tagged as safety was moved to Praise: general.

Sheet Summary
A1: Pull facts (full 3-month window, before sampling)
A3: App | B3: Play Store app ID | C3: Store title | D3: Pulled (UTC) | E3: Window | F3: Reviews in window | G3: 1★ | H3: 2★ | I3: 3★ | J3: 4★ | K3: 5★ | L3: 1★ share | M3: 5★ share | N3: Store rating (all-time) | O3: Tagged sample
A4: Uber | B4: com.ubercab | C4: Uber - Bike, Auto & Car Rides | D4: 2026-10-20 17:39 | E4: 2026-07-20 to 2026-10-19 | F4: 41073 | G4: 9733 | H4: 1123 | I4: 1084 | J4: 2287 | K4: 26846 | L4: =G4/F4 -> 0.23696832 | M4: =K4/F4 -> 0.65361673 | N4: 4.73 | O4: =COUNTIF(Reviews!$A:$A,A4) -> 3000
A5: Ola | B5: com.olacabs.customer | C5: Ola: Book Cab, Auto, Bike Taxi | D5: 2026-10-20 17:39 | E5: 2026-07-20 to 2026-10-19 | F5: 3754 | G5: 1944 | H5: 129 | I5: 112 | J5: 161 | K5: 1408 | L5: =G5/F5 -> 0.51784763 | M5: =K5/F5 -> 0.3750666 | N5: 4.61 | O5: =COUNTIF(Reviews!$A:$A,A5) -> 3000
A6: Rapido | B6: com.rapido.passenger | C6: Rapido: Bike-Taxi, Auto & Cabs | D6: 2026-10-20 17:39 | E6: 2026-07-20 to 2026-10-19 | F6: 35721 | G6: 10684 | H6: 926 | I6: 1058 | J6: 1879 | K6: 21174 | L6: =G6/F6 -> 0.29909577 | M6: =K6/F6 -> 0.59276056 | N6: 4.72 | O6: =COUNTIF(Reviews!$A:$A,A6) -> 3000
A7: Total | F7: =SUM(F4:F6) -> 80548 | G7: =SUM(G4:G6) -> 22361 | H7: =SUM(H4:H6) -> 2178 | I7: =SUM(I4:I6) -> 2254 | J7: =SUM(J4:J6) -> 4327 | K7: =SUM(K4:K6) -> 49428 | O7: =SUM(O4:O6) -> 9000
A9: Source: google-play-scraper, lang=en, country=in, sorted newest first. Store rating is Play's all-time average including star-only ratings.
A10: Ola got about 1 written review for every 11 on Uber in the same 3 months, and over half of them are 1 star.

Sheet Theme pivot
A1: Theme count and share, per app (random sample of 3,000 reviews each)
A3: Theme | B3: Type | C3: Uber | D3: Ola | E3: Rapido | F3: Uber % | G3: Ola % | H3: Rapido %
A4: Fare shown vs fare charged | B4: Complaint | C4: =COUNTIFS(Reviews!$A$2:$A$9001,"Uber",Reviews!$D$2:$D$9001,$A4) -> 199 | D4: =COUNTIFS(Reviews!$A$2:$A$9001,"Ola",Reviews!$D$2:$D$9001,$A4) -> 435 | E4: =COUNTIFS(Reviews!$A$2:$A$9001,"Rapido",Reviews!$D$2:$D$9001,$A4) -> 211 | F4: =C4/C$19 -> 0.066333333 | G4: =D4/D$19 -> 0.145 | H4: =E4/E$19 -> 0.070333333
A5: Driver cancels or refuses after accepting | B5: Complaint | C5: =COUNTIFS(Reviews!$A$2:$A$9001,"Uber",Reviews!$D$2:$D$9001,$A5) -> 90 | D5: =COUNTIFS(Reviews!$A$2:$A$9001,"Ola",Reviews!$D$2:$D$9001,$A5) -> 181 | E5: =COUNTIFS(Reviews!$A$2:$A$9001,"Rapido",Reviews!$D$2:$D$9001,$A5) -> 92 | F5: =C5/C$19 -> 0.03 | G5: =D5/D$19 -> 0.060333333 | H5: =E5/E$19 -> 0.030666667
A6: Support unreachable | B6: Complaint | C6: =COUNTIFS(Reviews!$A$2:$A$9001,"Uber",Reviews!$D$2:$D$9001,$A6) -> 73 | D6: =COUNTIFS(Reviews!$A$2:$A$9001,"Ola",Reviews!$D$2:$D$9001,$A6) -> 189 | E6: =COUNTIFS(Reviews!$A$2:$A$9001,"Rapido",Reviews!$D$2:$D$9001,$A6) -> 85 | F6: =C6/C$19 -> 0.024333333 | G6: =D6/D$19 -> 0.063 | H6: =E6/E$19 -> 0.028333333
A7: App bugs, login, maps | B7: Complaint | C7: =COUNTIFS(Reviews!$A$2:$A$9001,"Uber",Reviews!$D$2:$D$9001,$A7) -> 96 | D7: =COUNTIFS(Reviews!$A$2:$A$9001,"Ola",Reviews!$D$2:$D$9001,$A7) -> 156 | E7: =COUNTIFS(Reviews!$A$2:$A$9001,"Rapido",Reviews!$D$2:$D$9001,$A7) -> 113 | F7: =C7/C$19 -> 0.032 | G7: =D7/D$19 -> 0.052 | H7: =E7/E$19 -> 0.037666667
A8: No cab/auto/bike available | B8: Complaint | C8: =COUNTIFS(Reviews!$A$2:$A$9001,"Uber",Reviews!$D$2:$D$9001,$A8) -> 63 | D8: =COUNTIFS(Reviews!$A$2:$A$9001,"Ola",Reviews!$D$2:$D$9001,$A8) -> 157 | E8: =COUNTIFS(Reviews!$A$2:$A$9001,"Rapido",Reviews!$D$2:$D$9001,$A8) -> 88 | F8: =C8/C$19 -> 0.021 | G8: =D8/D$19 -> 0.052333333 | H8: =E8/E$19 -> 0.029333333
A9: Prices too high | B9: Complaint | C9: =COUNTIFS(Reviews!$A$2:$A$9001,"Uber",Reviews!$D$2:$D$9001,$A9) -> 86 | D9: =COUNTIFS(Reviews!$A$2:$A$9001,"Ola",Reviews!$D$2:$D$9001,$A9) -> 125 | E9: =COUNTIFS(Reviews!$A$2:$A$9001,"Rapido",Reviews!$D$2:$D$9001,$A9) -> 77 | F9: =C9/C$19 -> 0.028666667 | G9: =D9/D$19 -> 0.041666667 | H9: =E9/E$19 -> 0.025666667
A10: Long wait after booking | B10: Complaint | C10: =COUNTIFS(Reviews!$A$2:$A$9001,"Uber",Reviews!$D$2:$D$9001,$A10) -> 79 | D10: =COUNTIFS(Reviews!$A$2:$A$9001,"Ola",Reviews!$D$2:$D$9001,$A10) -> 85 | E10: =COUNTIFS(Reviews!$A$2:$A$9001,"Rapido",Reviews!$D$2:$D$9001,$A10) -> 58 | F10: =C10/C$19 -> 0.026333333 | G10: =D10/D$19 -> 0.028333333 | H10: =E10/E$19 -> 0.019333333
A11: Safety | B11: Complaint | C11: =COUNTIFS(Reviews!$A$2:$A$9001,"Uber",Reviews!$D$2:$D$9001,$A11) -> 17 | D11: =COUNTIFS(Reviews!$A$2:$A$9001,"Ola",Reviews!$D$2:$D$9001,$A11) -> 43 | E11: =COUNTIFS(Reviews!$A$2:$A$9001,"Rapido",Reviews!$D$2:$D$9001,$A11) -> 58 | F11: =C11/C$19 -> 0.0056666667 | G11: =D11/D$19 -> 0.014333333 | H11: =E11/E$19 -> 0.019333333
A12: Cash vs UPI, payments, refunds | B12: Complaint | C12: =COUNTIFS(Reviews!$A$2:$A$9001,"Uber",Reviews!$D$2:$D$9001,$A12) -> 47 | D12: =COUNTIFS(Reviews!$A$2:$A$9001,"Ola",Reviews!$D$2:$D$9001,$A12) -> 81 | E12: =COUNTIFS(Reviews!$A$2:$A$9001,"Rapido",Reviews!$D$2:$D$9001,$A12) -> 20 | F12: =C12/C$19 -> 0.015666667 | G12: =D12/D$19 -> 0.027 | H12: =E12/E$19 -> 0.0066666667
A13: Rude driver or vehicle condition | B13: Complaint | C13: =COUNTIFS(Reviews!$A$2:$A$9001,"Uber",Reviews!$D$2:$D$9001,$A13) -> 29 | D13: =COUNTIFS(Reviews!$A$2:$A$9001,"Ola",Reviews!$D$2:$D$9001,$A13) -> 65 | E13: =COUNTIFS(Reviews!$A$2:$A$9001,"Rapido",Reviews!$D$2:$D$9001,$A13) -> 50 | F13: =C13/C$19 -> 0.0096666667 | G13: =D13/D$19 -> 0.021666667 | H13: =E13/E$19 -> 0.016666667
A14: Vague or other complaint | B14: Complaint | C14: =COUNTIFS(Reviews!$A$2:$A$9001,"Uber",Reviews!$D$2:$D$9001,$A14) -> 141 | D14: =COUNTIFS(Reviews!$A$2:$A$9001,"Ola",Reviews!$D$2:$D$9001,$A14) -> 217 | E14: =COUNTIFS(Reviews!$A$2:$A$9001,"Rapido",Reviews!$D$2:$D$9001,$A14) -> 236 | F14: =C14/C$19 -> 0.047 | G14: =D14/D$19 -> 0.072333333 | H14: =E14/E$19 -> 0.078666667
A15: Praise: general | B15: Praise | C15: =COUNTIFS(Reviews!$A$2:$A$9001,"Uber",Reviews!$D$2:$D$9001,$A15) -> 1634 | D15: =COUNTIFS(Reviews!$A$2:$A$9001,"Ola",Reviews!$D$2:$D$9001,$A15) -> 985 | E15: =COUNTIFS(Reviews!$A$2:$A$9001,"Rapido",Reviews!$D$2:$D$9001,$A15) -> 1630 | F15: =C15/C$19 -> 0.54466667 | G15: =D15/D$19 -> 0.32833333 | H15: =E15/E$19 -> 0.54333333
... A18: Unclear or off-topic | B18: Other | C18: =COUNTIFS(Reviews!$A$2:$A$9001,"Uber",Reviews!$D$2:$D$9001,$A18) -> 77 | D18: =COUNTIFS(Reviews!$A$2:$A$9001,"Ola",Reviews!$D$2:$D$9001,$A18) -> 100 | E18: =COUNTIFS(Reviews!$A$2:$A$9001,"Rapido",Reviews!$D$2:$D$9001,$A18) -> 94 | F18: =C18/C$19 -> 0.025666667 | G18: =D18/D$19 -> 0.033333333 | H18: =E18/E$19 -> 0.031333333
A19: Total | C19: =SUM(C4:C18) -> 3000 | D19: =SUM(D4:D18) -> 3000 | E19: =SUM(E4:E18) -> 3000 | F19: =SUM(F4:F18) -> 1 | G19: =SUM(G4:G18) -> 1 | H19: =SUM(H4:H18) -> 1
A20: Rows sorted with the 10 named complaints first. Shares are of all sampled reviews for that app.
A22: Inside 'Fare shown vs fare charged': what actually happened
A23: Fare subtype | C23: Uber | D23: Ola | E23: Rapido | F23: Uber % of all | G23: Ola % of all | H23: Rapido % of all
A24: Driver asked for more than the app fare | C24: =COUNTIFS(Reviews!$A$2:$A$9001,"Uber",Reviews!$G$2:$G$9001,$A24) -> 73 | D24: =COUNTIFS(Reviews!$A$2:$A$9001,"Ola",Reviews!$G$2:$G$9001,$A24) -> 277 | E24: =COUNTIFS(Reviews!$A$2:$A$9001,"Rapido",Reviews!$G$2:$G$9001,$A24) -> 120 | F24: =C24/C$19 -> 0.024333333 | G24: =D24/D$19 -> 0.092333333 | H24: =E24/E$19 -> 0.04
A25: In-app final fare higher than quoted | C25: =COUNTIFS(Reviews!$A$2:$A$9001,"Uber",Reviews!$G$2:$G$9001,$A25) -> 93 | D25: =COUNTIFS(Reviews!$A$2:$A$9001,"Ola",Reviews!$G$2:$G$9001,$A25) -> 122 | E25: =COUNTIFS(Reviews!$A$2:$A$9001,"Rapido",Reviews!$G$2:$G$9001,$A25) -> 69 | F25: =C25/C$19 -> 0.031 | G25: =D25/D$19 -> 0.040666667 | H25: =E25/E$19 -> 0.023
A26: Unexpected fee (cancel, platform) | C26: =COUNTIFS(Reviews!$A$2:$A$9001,"Uber",Reviews!$G$2:$G$9001,$A26) -> 15 | D26: =COUNTIFS(Reviews!$A$2:$A$9001,"Ola",Reviews!$G$2:$G$9001,$A26) -> 26 | E26: =COUNTIFS(Reviews!$A$2:$A$9001,"Rapido",Reviews!$G$2:$G$9001,$A26) -> 14 | F26: =C26/C$19 -> 0.005 | G26: =D26/D$19 -> 0.0086666667 | H26: =E26/E$19 -> 0.0046666667
A27: Surge before booking | C27: =COUNTIFS(Reviews!$A$2:$A$9001,"Uber",Reviews!$G$2:$G$9001,$A27) -> 13 | D27: =COUNTIFS(Reviews!$A$2:$A$9001,"Ola",Reviews!$G$2:$G$9001,$A27) -> 7 | E27: =COUNTIFS(Reviews!$A$2:$A$9001,"Rapido",Reviews!$G$2:$G$9001,$A27) -> 6 | F27: =C27/C$19 -> 0.0043333333 | G27: =D27/D$19 -> 0.0023333333 | H27: =E27/E$19 -> 0.002
A28: Other fare issue | C28: =COUNTIFS(Reviews!$A$2:$A$9001,"Uber",Reviews!$G$2:$G$9001,$A28) -> 5 | D28: =COUNTIFS(Reviews!$A$2:$A$9001,"Ola",Reviews!$G$2:$G$9001,$A28) -> 3 | E28: =COUNTIFS(Reviews!$A$2:$A$9001,"Rapido",Reviews!$G$2:$G$9001,$A28) -> 2 | F28: =C28/C$19 -> 0.0016666667 | G28: =D28/D$19 -> 0.001 | H28: =E28/E$19 -> 0.00066666667

Sheet Quotes
A1: Real reviews behind each app's top 3 complaints
A2: Verbatim, with phone numbers, UPI IDs and number plates masked. Spelling left as written.
A4: App | B4: Theme | C4: Share of app's reviews | D4: Stars | E4: Review
A5: Uber | B5: Fare shown vs fare charged | C5: =INDEX('Theme pivot'!$F$4:$H$18,MATCH(B5,'Theme pivot'!$A$4:$A$18,0),MATCH(A5,'Theme pivot'!$C$3:$E$3,0)) -> 0.066333333 | D5: 2 | E5: while Booking showing some rate and when we reach destination showing increased rate by more than 20%
A6: Uber | B6: Fare shown vs fare charged | C6: =INDEX('Theme pivot'!$F$4:$H$18,MATCH(B6,'Theme pivot'!$A$4:$A$18,0),MATCH(A6,'Theme pivot'!$C$3:$E$3,0)) -> 0.066333333 | D6: 1 | E6: poor service. when you book the ride , the amount is different. as soon as you reach always the amount increases , even if you take the same route daily and no traffic etc. fraud
A7: Uber | B7: App bugs, login, maps | C7: =INDEX('Theme pivot'!$F$4:$H$18,MATCH(B7,'Theme pivot'!$A$4:$A$18,0),MATCH(A7,'Theme pivot'!$C$3:$E$3,0)) -> 0.032 | D7: 2 | E7: The amount of ads, pop-ups and annoying offers is extremely high. The app is poorly designed, and hardly intuitive.
A8: Uber | B8: App bugs, login, maps | C8: =INDEX('Theme pivot'!$F$4:$H$18,MATCH(B8,'Theme pivot'!$A$4:$A$18,0),MATCH(A8,'Theme pivot'!$C$3:$E$3,0)) -> 0.032 | D8: 1 | E8: for the last week, I can't book a ride because it doesn't accept any of my credit cards. pls fix it immediately
A9: Uber | B9: Driver cancels or refuses after accepting | C9: =INDEX('Theme pivot'!$F$4:$H$18,MATCH(B9,'Theme pivot'!$A$4:$A$18,0),MATCH(A9,'Theme pivot'!$C$3:$E$3,0)) -> 0.03 | D9: 3 | E9: Drivers who cancels should have a fine as well for accepting then cancelling.. been dealing with it everytime.
A10: Uber | B10: Driver cancels or refuses after accepting | C10: =INDEX('Theme pivot'!$F$4:$H$18,MATCH(B10,'Theme pivot'!$A$4:$A$18,0),MATCH(A10,'Theme pivot'!$C$3:$E$3,0)) -> 0.03 | D10: 1 | E10: Bike riders is very bad 👎 conform trip hone par kahte hain aayenge baad me cancel kar dete hain and 1 se 2 ghante lagate hain bike wale conform trip karne ke liye
A11: Ola | B11: Fare shown vs fare charged | C11: =INDEX('Theme pivot'!$F$4:$H$18,MATCH(B11,'Theme pivot'!$A$4:$A$18,0),MATCH(A11,'Theme pivot'!$C$3:$E$3,0)) -> 0.145 | D11: 1 | E11: very bad experience i booked a bike ride showing a fare of 122, but after the Trip was completed , it increased to 180 and the driver's behaviour was very bad. This app is not responsible at all.
A12: Ola | B12: Fare shown vs fare charged | C12: =INDEX('Theme pivot'!$F$4:$H$18,MATCH(B12,'Theme pivot'!$A$4:$A$18,0),MATCH(A12,'Theme pivot'!$C$3:$E$3,0)) -> 0.145 | D12: 2 | E12: The government has banned advance tips, still your app shows that option. Also, it shows the fare amount in the app but the driver says charges will be 25 rs/km which are much more than what's shown in the app. what is this?
A13: Ola | B13: Support unreachable | C13: =INDEX('Theme pivot'!$F$4:$H$18,MATCH(B13,'Theme pivot'!$A$4:$A$18,0),MATCH(A13,'Theme pivot'!$C$3:$E$3,0)) -> 0.063 | D13: 1 | E13: dumbest app, doesn't allow you to contact customer support... The driver has collected extra money but I'm unable to report it on the app.
A14: Ola | B14: Support unreachable | C14: =INDEX('Theme pivot'!$F$4:$H$18,MATCH(B14,'Theme pivot'!$A$4:$A$18,0),MATCH(A14,'Theme pivot'!$C$3:$E$3,0)) -> 0.063 | D14: 1 | E14: Most frustrating customer care , grievance and nodal office setup to kill our time. its been more than a month have wrote so many emails but never ever got a single reply. Seems they plan to close operations.
A15: Ola | B15: Driver cancels or refuses after accepting | C15: =INDEX('Theme pivot'!$F$4:$H$18,MATCH(B15,'Theme pivot'!$A$4:$A$18,0),MATCH(A15,'Theme pivot'!$C$3:$E$3,0)) -> 0.060333333 | D15: 1 | E15: You people need to focus on your own app. The auto drivers are asking customers to cancel the online booking and go by the meter instead. On top of that, there is absolutely no customer support or help available.
A16: Ola | B16: Driver cancels or refuses after accepting | C16: =INDEX('Theme pivot'!$F$4:$H$18,MATCH(B16,'Theme pivot'!$A$4:$A$18,0),MATCH(A16,'Theme pivot'!$C$3:$E$3,0)) -> 0.060333333 | D16: 1 | E16: After accepting the ride, the driver did not come and he was telling me to cancel the ride. if he didn't want to come then why did he accept the ride?
... A22: Rapido | B22: Driver cancels or refuses after accepting | C22: =INDEX('Theme pivot'!$F$4:$H$18,MATCH(B22,'Theme pivot'!$A$4:$A$18,0),MATCH(A22,'Theme pivot'!$C$3:$E$3,0)) -> 0.030666667 | D22: 1 | E22: frequently I used Rapido.but today's captain cancel my ride without knowing me.because he is asking for extra money.I told him,first you reach me.after that i will think.today i am late in my office.very bad experience fill today

Sheet Validation
A1: Validation: 50 random tags checked by hand
A2: I drew 50 reviews at random from the 9,000 (seed 7) and labelled each one myself before looking at the model's tag.
B3: Exact agreement | E3: =SUM(G7:G56)/COUNTA(G7:G56) -> 0.84 | F3: =SUM(G7:G56)&" of "&COUNTA(G7:G56) -> 42 of 50
B4: Same direction (complaint vs praise vs unclear) | E4: =SUM(H7:H56)/COUNTA(H7:H56) -> 0.96
A6: # | B6: App | C6: Stars | D6: Review (anonymised) | E6: Model's tag | F6: My tag | G6: Match | H6: Same direction | I6: Why we differ
A7: 1 | B7: Ola | C7: 5 | D7: 👍 ❤️👌 | E7: Praise: general | F7: Praise: general | G7: =IF(E7=F7,1,0) -> 1 | H7: 1
A8: 2 | B8: Ola | C8: 3 | D8: It's good overall but sometimes It takes hours to confirm one ride. | E8: Long wait after booking | F8: No cab/auto/bike available | G8: =IF(E8=F8,1,0) -> 0 | H8: 1
A9: 3 | B9: Uber | C9: 5 | D9: good traveling 😃 | E9: Praise: general | F9: Praise: general | G9: =IF(E9=F9,1,0) -> 1 | H9: 1
A10: 4 | B10: Rapido | C10: 5 | D10: one of the best drivers | E10: Praise: driver | F10: Praise: driver | G10: =IF(E10=F10,1,0) -> 1 | H10: 1
A11: 5 | B11: Ola | C11: 1 | D11: ola money bad ai Call total frud muze pareshan kardiy plz company number | E11: Cash vs UPI, payments, refunds | F11: Cash vs UPI, payments, refunds | G11: =IF(E11=F11,1,0) -> 1 | H11: 1
A12: 6 | B12: Ola | C12: 1 | D12: Very Poor Service & No Proper Customer Support I had a very bad experience with Ola. When I faced an issue with the auto driver, there was no proper way to get help or speak to a customer-care representative. The app and website do not provide an easily accessible helpline for resolving serious complaints. The auto driver was extremely rude and disrespectful. He shouted at me, behaved badly, and charged extra for the ride. Most importantly, his behaviour made me feel unsafe. | E12: Safety | F12: Rude driver or vehicle condition | G12: =IF(E12=F12,1,0) -> 0 | H12: 1 | I12: Also says support unreachable; I picked the driver because he caused it
A13: 7 | B13: Uber | C13: 5 | D13: good | E13: Praise: general | F13: Praise: general | G13: =IF(E13=F13,1,0) -> 1 | H13: 1
A14: 8 | B14: Uber | C14: 5 | D14: good ride | E14: Praise: general | F14: Praise: general | G14: =IF(E14=F14,1,0) -> 1 | H14: 1
A15: 9 | B15: Rapido | C15: 5 | D15: very good | E15: Praise: general | F15: Praise: general | G15: =IF(E15=F15,1,0) -> 1 | H15: 1
A16: 10 | B16: Uber | C16: 5 | D16: good | E16: Praise: general | F16: Praise: general | G16: =IF(E16=F16,1,0) -> 1 | H16: 1
A17: 11 | B17: Uber | C17: 5 | D17: good human being the driver | E17: Praise: driver | F17: Praise: driver | G17: =IF(E17=F17,1,0) -> 1 | H17: 1
A18: 12 | B18: Rapido | C18: 5 | D18: please decrease the price little for us | E18: Prices too high | F18: Prices too high | G18: =IF(E18=F18,1,0) -> 1 | H18: 1
A19: 13 | B19: Ola | C19: 4 | D19: Drivers cancel quite often leading to risk in missing trains or flights | E19: Driver cancels or refuses after accepting | F19: Driver cancels or refuses after accepting | G19: =IF(E19=F19,1,0) -> 1 | H19: 1
A20: 14 | B20: Rapido | C20: 5 | D20: best | E20: Praise: general | F20: Praise: general | G20: =IF(E20=F20,1,0) -> 1 | H20: 1
A21: 15 | B21: Ola | C21: 5 | D21: best service.. | E21: Praise: general | F21: Praise: general | G21: =IF(E21=F21,1,0) -> 1 | H21: 1
A22: 16 | B22: Uber | C22: 5 | D22: faster than ola | E22: Praise: general | F22: Praise: general | G22: =IF(E22=F22,1,0) -> 1 | H22: 1
A23: 17 | B23: Ola | C23: 5 | D23: maintained time factor punctual and polite behavior with all respect reached home safely 🙏 | E23: Praise: driver | F23: Praise: driver | G23: =IF(E23=F23,1,0) -> 1 | H23: 1
A24: 18 | B24: Rapido | C24: 5 | D24: good | E24: Praise: general | F24: Praise: general | G24: =IF(E24=F24,1,0) -> 1 | H24: 1
... A28: 22 | B28: Uber | C28: 5 | D28: very useful | E28: Praise: general | F28: Praise: general | G28: =IF(E28=F28,1,0) -> 1 | H28: 1
A29: 23 | B29: Rapido | C29: 1 | D29: In this app whenever I try to book auto in urgent first of all it doesn't get book, second it shows the fare price and try to book it doesn't book only and everytime I have pay double the amount for same distance. And it take to long get book also. It is my worst experience in my urgent. if anyone trying to download please don't depend on one single app use different app also | E29: Fare shown vs fare charged | F29: No cab/auto/bike available | G29: =IF(E29=F29,1,0) -> 0 | H29: 1 | I29: Also says fare doubled; booking failure came first
A30: 24 | B30: Uber | C30: 1 | D30: Over suspense, driver app and does not tell me why ..I am entitled of knowing why I am been investigation. I have tried to get in contact with them but I feel like I'm talking to a computer. The Same blah blah blah blah.. But I feel that that's unfair, I'd like to know what I've been investigator..... They don't care that I gotta feed my family. it looks like 10 years of loyalty does not help, yeah. So consider a situation before you start working with them. I am | E30: Support unreachable | F30: Vague or other complaint | G30: =IF(E30=F30,1,0) -> 0 | H30: 1 | I30: Driver-side review about account suspension, not a rider
A31: 25 | B31: Uber | C31: 5 | D31: good work | E31: Praise: general | F31: Praise: general | G31: =IF(E31=F31,1,0) -> 1 | H31: 1
A32: 26 | B32: Ola | C32: 1 | D32: so much system glitch. not able to book rides | E32: App bugs, login, maps | F32: App bugs, login, maps | G32: =IF(E32=F32,1,0) -> 1 | H32: 1
A33: 27 | B33: Uber | C33: 1 | D33: Uber treats drivers and customers with equal disrespect. We had reserved an Uber Pet to pick us up from a remote location but when the driver arrived he was caught by surprise that there was a dog since he had opted out of accepting pet rides. Uber support then suggested to him that of course he could cancel that ride which would have left us stranded and miss our flight. In the end he did take us, but this level of uncertainty and stress caused by Uber (not the driver) is unacceptable. | E33: Driver cancels or refuses after accepting | F33: Vague or other complaint | G33: =IF(E33=F33,1,0) -> 0 | H33: 1 | I33: US review (Uber Pet); fits no theme cleanly
A34: 28 | B34: Uber | C34: 5 | D34: very good service 👏 | E34: Praise: general | F34: Praise: general | G34: =IF(E34=F34,1,0) -> 1 | H34: 1
A35: 29 | B35: Ola | C35: 1 | D35: Ransoming for money due to drivers fault. I uninstalled it. | E35: Fare shown vs fare charged | F35: Fare shown vs fare charged | G35: =IF(E35=F35,1,0) -> 1 | H35: 1
A36: 30 | B36: Uber | C36: 5 | D36: good driver and good driving | E36: Praise: driver | F36: Praise: driver | G36: =IF(E36=F36,1,0) -> 1 | H36: 1
A37: 31 | B37: Uber | C37: 5 | D37: very good 👍 | E37: Praise: general | F37: Praise: general | G37: =IF(E37=F37,1,0) -> 1 | H37: 1
A38: 32 | B38: Ola | C38: 1 | D38: Doesn't take near by rides | E38: No cab/auto/bike available | F38: Driver cancels or refuses after accepting | G38: =IF(E38=F38,1,0) -> 0 | H38: 1
A39: 33 | B39: Ola | C39: 1 | D39: drivers not available when needed waste of time | E39: No cab/auto/bike available | F39: No cab/auto/bike available | G39: =IF(E39=F39,1,0) -> 1 | H39: 1
A40: 34 | B40: Rapido | C40: 1 | D40: Totally waste and iressponsible captains, if we try to book a bike or Auto, thry wont accept the rides on lots of time and also taking too long to confirm the ride. Actually totaly waste to use thos Rapido.... Waste | E40: No cab/auto/bike available | F40: No cab/auto/bike available | G40: =IF(E40=F40,1,0) -> 1 | H40: 1
A41: 35 | B41: Uber | C41: 5 | D41: very good | E41: Praise: general | F41: Praise: general | G41: =IF(E41=F41,1,0) -> 1 | H41: 1
A42: 36 | B42: Rapido | C42: 1 | D42: worst app ever, drivers are always late and never on time, neither they accept the ride and after accepting they ask us to cancel the ride, wow. | E42: Driver cancels or refuses after accepting | F42: Driver cancels or refuses after accepting | G42: =IF(E42=F42,1,0) -> 1 | H42: 1
A43: 37 | B43: Rapido | C43: 1 | D43: worst app your so called cheap drivers ask for extra money always and we give it to them and what u do in return if they ask for extra money and we cancel then also we need to pay extra 10 rupees ur app is just looting people and nothing else | E43: Fare shown vs fare charged | F43: Fare shown vs fare charged | G43: =IF(E43=F43,1,0) -> 1 | H43: 1
A44: 38 | B44: Ola | C44: 1 | D44: नवी मुंबई एयरपोर्ट से बेलापुर रेलवे स्टेशन की 4 km दूरी है जिसका किराया 700 से 800 तक ओला दिखता है 500 की जगह पर 1600 किराया आता | E44: Fare shown vs fare charged | F44: Fare shown vs fare charged | G44: =IF(E44=F44,1,0) -> 1 | H44: 1
A45: 39 | B45: Uber | C45: 5 | D45: super | E45: Praise: general | F45: Praise: general | G45: =IF(E45=F45,1,0) -> 1 | H45: 1
... A48: 42 | B48: Uber | C48: 5 | D48: good | E48: Praise: general | F48: Praise: general | G48: =IF(E48=F48,1,0) -> 1 | H48: 1
A49: 43 | B49: Uber | C49: 1 | D49: worst experience in peak time | E49: Vague or other complaint | F49: Unclear or off-topic | G49: =IF(E49=F49,1,0) -> 0 | H49: 0 | I49: Could be pricing or availability; not enough to tell
A50: 44 | B50: Ola | C50: 1 | D50: jaldi boking nahi hota h or hoga bhi to drivr extra cash bolnge or aane me late ....high fair bohat despoint karta h app kabhi kabhi please captin ko bole or unko sahi payment karo ki vo hum log se zyda demand na kare | E50: Fare shown vs fare charged | F50: Fare shown vs fare charged | G50: =IF(E50=F50,1,0) -> 1 | H50: 1
A51: 45 | B51: Uber | C51: 5 | D51: good | E51: Praise: general | F51: Praise: general | G51: =IF(E51=F51,1,0) -> 1 | H51: 1
A52: 46 | B52: Ola | C52: 5 | D52: nice | E52: Praise: general | F52: Praise: general | G52: =IF(E52=F52,1,0) -> 1 | H52: 1
A53: 47 | B53: Uber | C53: 5 | D53: Drivers polite and professional. Best price available for quick transport in the city. | E53: Praise: driver | F53: Praise: driver | G53: =IF(E53=F53,1,0) -> 1 | H53: 1
A54: 48 | B54: Ola | C54: 1 | D54: very bad service | E54: Vague or other complaint | F54: Unclear or off-topic | G54: =IF(E54=F54,1,0) -> 0 | H54: 0
A55: 49 | B55: Ola | C55: 1 | D55: very bad experience looks like ola drivers always ask for extra money company should look after these goons | E55: Fare shown vs fare charged | F55: Fare shown vs fare charged | G55: =IF(E55=F55,1,0) -> 1 | H55: 1
A56: 50 | B56: Rapido | C56: 5 | D56: good 👍 | E56: Praise: general | F56: Praise: general | G56: =IF(E56=F56,1,0) -> 1 | H56: 1

Sheet Themes
A1: Theme definitions given to the model
A3: Theme | B3: Key | C3: Definition
A4: Driver cancels or refuses after accepting | B4: driver_cancel | C4: Driver cancels after accepting, refuses the trip, asks the rider to cancel, asks destination/payment mode before coming, or never shows up
A5: Fare shown vs fare charged | B5: fare_mismatch | C5: Final fare higher than the fare shown at booking, surprise surge, extra charges added, driver demands more than the app fare
A6: Prices too high | B6: high_prices | C6: General complaint that fares or surge are too expensive, without a shown-vs-charged gap
A7: Cash vs UPI, payments, refunds | B7: payment_dispute | C7: Cash vs UPI/online fights, paid twice, money deducted but trip unpaid, wallet or refund not received
A8: Safety | B8: safety | C8: Feeling unsafe: rash or drunk driving, harassment, threats, wrong route at night, vehicle unsafe
A9: Rude driver or vehicle condition | B9: driver_behaviour | C9: Rude or unprofessional driver, AC off, dirty vehicle, wrong vehicle or number plate, smoking (not a safety threat)
A10: Support unreachable | B10: support | C10: Can't reach customer support, bot-only help, complaint ignored or not resolved
A11: App bugs, login, maps | B11: app_bugs | C11: App crashes or freezes, login/OTP/account problems, wrong pickup location or map, booking or payment screen errors
A12: No cab/auto/bike available | B12: availability | C12: No driver/auto/bike found, no captain assigned, service not available in the area
A13: Long wait after booking | B13: wait_time | C13: Driver accepted but takes too long, ETA keeps growing, driver not moving towards pickup
A14: Vague or other complaint | B14: other_complaint | C14: A clear complaint that fits none of the above
... A18: Unclear or off-topic | B18: unclear | C18: Too short or vague to tell, gibberish, off-topic

Sheet Reviews
A1: App | B1: Date | C1: Stars | D1: Theme | E1: Theme key | F1: Sentiment | G1: Fare subtype | H1: Review (anonymised) | I1: Thumbs up | J1: App version
A2: Ola | B2: 46314.724 | C2: 1 | D2: Driver cancels or refuses after accepting | E2: driver_cancel | F2: neg | H2: worst experience. I had booked a cab the driver asked me to cancel the ride. i cancelled it and later realised I got a deduction of 60rs. So the driver did it on purpose. And to complain this there is no medium at all to connect with the agent | I2: 0 | J2: 7.6.1
A3: Ola | B3: 46314.686 | C3: 5 | D3: Praise: general | E3: praise_general | F3: pos | H3: top | I3: 0 | J3: 7.5.9
A4: Ola | B4: 46314.667 | C4: 1 | D4: Support unreachable | E4: support | F4: neg | H4: worst experience with the customer service | I4: 0 | J4: 7.6.1
A5: Ola | B5: 46314.656 | C5: 5 | D5: Praise: driver | E5: praise_driver | F5: pos | H5: good driver | I5: 0 | J5: 7.6.1
A6: Ola | B6: 46314.653 | C6: 1 | D6: Vague or other complaint | E6: other_complaint | F6: neg | H6: veri veri veri veri veri veri veri veri veri poor Ola no time no fastest is not language in very poor Ola | I6: 0
A7: Ola | B7: 46314.652 | C7: 1 | D7: Driver cancels or refuses after accepting | E7: driver_cancel | F7: neg | H7: bad service. captain not accepting ride. if some accepted they cancelled | I7: 0 | J7: 7.5.8
A8: Ola | B8: 46314.643 | C8: 4 | D8: Praise: general | E8: praise_general | F8: pos | H8: good 👍 | I8: 0 | J8: 7.5.8
A9: Ola | B9: 46314.61 | C9: 1 | D9: Vague or other complaint | E9: other_complaint | F9: neg | H9: ola very bed service | I9: 0 | J9: 7.6.1
A10: Ola | B10: 46314.589 | C10: 5 | D10: Praise: general | E10: praise_general | F10: pos | H10: good service | I10: 0 | J10: 7.6.1
A11: Ola | B11: 46314.577 | C11: 1 | D11: Vague or other complaint | E11: other_complaint | F11: neg | H11: ghatiya app | I11: 0 | J11: 7.6.1
A12: Ola | B12: 46314.549 | C12: 5 | D12: Praise: general | E12: praise_general | F12: pos | H12: Good service | I12: 0 | J12: 7.6.1
A13: Ola | B13: 46314.541 | C13: 1 | D13: Cash vs UPI, payments, refunds | E13: payment_dispute | F13: neg | H13: worst response from support team. I had directly maid the payment to the driver but the app is showing outstanding. despite sending multiple emails and tried to reach grivience team I am not getting response. they don't have a toll free number to reach and just keep sending reminders. Would never recommend someone to use ola and try other options available. | I13: 0 | J13: 7.6.1
A14: Ola | B14: 46314.528 | C14: 1 | D14: Fare shown vs fare charged | E14: fare_mismatch | F14: neg | G14: In-app final fare higher than quoted | H14: it's a scam , first they show small fare and then after booking a different amount shows. then afterwards no option to contact support. | I14: 0 | J14: 7.6.1
A15: Ola | B15: 46314.52 | C15: 5 | D15: Praise: general | E15: praise_general | F15: pos | H15: Very good service | I15: 0 | J15: 7.5.2
A16: Ola | B16: 46314.515 | C16: 5 | D16: Praise: general | E16: praise_general | F16: pos | H16: good | I16: 0 | J16: 7.6.1
A17: Ola | B17: 46314.489 | C17: 5 | D17: Praise: general | E17: praise_general | F17: pos | H17: good | I17: 0 | J17: 7.5.9
A18: Ola | B18: 46314.423 | C18: 5 | D18: Praise: general | E18: praise_general | F18: pos | H18: nice | I18: 0 | J18: 7.5.9
A19: Ola | B19: 46314.391 | C19: 5 | D19: Praise: general | E19: praise_general | F19: pos | H19: good 👍 | I19: 0 | J19: 7.6.1
A20: Ola | B20: 46314.39 | C20: 5 | D20: Praise: driver | E20: praise_driver | F20: pos | H20: good driver | I20: 0 | J20: 7.5.9
A21: Ola | B21: 46314.388 | C21: 5 | D21: Praise: general | E21: praise_general | F21: pos | H21: super | I21: 0 | J21: 7.5.6
A22: Ola | B22: 46314.383 | C22: 1 | D22: Support unreachable | E22: support | F22: neg | H22: I'm to login since 3 months and no one helping and there is no call number | I22: 0 | J22: 7.6.1
A23: Ola | B23: 46314.233 | C23: 1 | D23: Cash vs UPI, payments, refunds | E23: payment_dispute | F23: neg | H23: Don't go with Ola they don't have any direct number for your queries. Money deducted from my account but the driver didn't receive it and I pay with UPI. When I tried to contact them there was no direct number and I mailed them and they gave me a new token number for every single mail but no solution no reply no call. So uninstall these types of fraud apps. | I23: 0 | J23: 7.6.1
A24: Ola | B24: 46314.216 | C24: 1 | D24: Fare shown vs fare charged | E24: fare_mismatch | F24: neg | G24: Driver asked for more than the app fare | H24: bahut bakwas ho gaya hai ye app pahle sahi tha ab kam se kam ₹20 extra do to koi call leta hai apne hisab se route ab select hi nahi kar sakte wo jis route se dikha usme bahut gadde the 2 km extra alag route se to 70 rupee extra le liya driver ne ... thoooo app aj hi uninstall kar dunga... | I24: 0 | J24: 7.6.1
A25: Ola | B25: 46314.182 | C25: 5 | D25: Praise: general | E25: praise_general | F25: pos | H25: nice | I25: 0 | J25: 7.6.1
A26: Ola | B26: 46314.18 | C26: 5 | D26: Praise: general | E26: praise_general | F26: pos | H26: helpful | I26: 0 | J26: 7.6.1
A27: Ola | B27: 46314.166 | C27: 5 | D27: Praise: general | E27: praise_general | F27: pos | H27: good service | I27: 0 | J27: 7.5.9
A28: Ola | B28: 46314.158 | C28: 1 | D28: No cab/auto/bike available | E28: availability | F28: neg | H28: despite of trying 4 times with different types of ride each time, no one accepted. worst service. | I28: 0 | J28: 7.5.6
A29: Ola | B29: 46314.076 | C29: 5 | D29: Praise: general | E29: praise_general | F29: pos | H29: nice | I29: 0 | J29: 7.6.1
A30: Ola | B30: 46313.921 | C30: 5 | D30: Praise: general | E30: praise_general | F30: pos | H30: good | I30: 0 | J30: 7.5.9
A31: Ola | B31: 46313.74 | C31: 1 | D31: Fare shown vs fare charged | E31: fare_mismatch | F31: neg | G31: In-app final fare higher than quoted | H31: very bad app for ride they're charge extra money without region | I31: 0 | J31: 7.5.3
A32: Ola | B32: 46313.716 | C32: 2 | D32: Fare shown vs fare charged | E32: fare_mismatch | F32: neg | G32: Driver asked for more than the app fare | H32: one ola car driver charged me 650/-₹ instead of 389/-₹. Actually he refused charges as per old fare and charged 25₹ per km in pune. also he took long route. | I32: 0 | J32: 7.5.9
A33: Ola | B33: 46313.649 | C33: 5 | D33: Praise: general | E33: praise_general | F33: pos | H33: excellent experience . | I33: 0 | J33: 7.6.1
A34: Ola | B34: 46313.647 | C34: 5 | D34: Praise: driver | E34: praise_driver | F34: pos | H34: This drive was excellent as the driver went out of the way to help us reach the destination inspite of the rain water. We could reach the railway station on time. | I34: 0 | J34: 7.5.9
A35: Ola | B35: 46313.568 | C35: 5 | D35: Praise: general | E35: praise_general | F35: pos | H35: overall good | I35: 0 | J35: 4.0.4
A36: Ola | B36: 46313.536 | C36: 1 | D36: Long wait after booking | E36: wait_time | F36: neg | H36: ola dusra kuch try kar mera dost bola😂😂 aaj book karo captain kal aata hai | I36: 0 | J36: 7.6.1
A37: Ola | B37: 46313.521 | C37: 1 | D37: Fare shown vs fare charged | E37: fare_mismatch | F37: neg | G37: In-app final fare higher than quoted | H37: At the time of booking, the price was less, but after completing the ride, they asked for extra money. | I37: 0
A38: Ola | B38: 46313.376 | C38: 3 | D38: Vague or other complaint | E38: other_complaint | F38: neg | H38: service slow | I38: 0 | J38: 7.5.9
A39: Ola | B39: 46313.361 | C39: 5 | D39: Praise: general | E39: praise_general | F39: pos | H39: Good service | I39: 0 | J39: 7.5.9
A40: Ola | B40: 46313.346 | C40: 1 | D40: Support unreachable | E40: support | F40: neg | H40: i would rate 0 or -1 to Ola this worst company towards customer after deducting money they will not reply on Email Better to use local Taxi , or other App Avoid OlA please if u want to be safe from Fraud 🤥🤥🤥 | I40: 0
A41: Ola | B41: 46313.33 | C41: 3 | D41: Unclear or off-topic | E41: unclear | F41: neutral | H41: well | I41: 0 | J41: 7.5.8
A42: Ola | B42: 46313.314 | C42: 1 | D42: Support unreachable | E42: support | F42: neg | H42: I was very disappointed with the support of the OLA staff , continuously I am trying to establish a contact to get my OLA account so that I am able to again use the rides of this. but unfortunately they are not responding even at mail and no contact number is available to contact them directly..... hole they will resolve my issue. | I42: 0 | J42: 7.5.8
A43: Ola | B43: 46313.3 | C43: 5 | D43: Praise: general | E43: praise_general | F43: pos | H43: good service. we are happy | I43: 0 | J43: 7.5.6
A44: Ola | B44: 46313.293 | C44: 1 | D44: Fare shown vs fare charged | E44: fare_mismatch | F44: neg | G44: In-app final fare higher than quoted | H44: When Ola first launched its service, it worked well; however, the service has become quite poor lately. The final fare often ends up being higher than the amount shown at the time of booking. Overall, the service is increasingly becoming unsatisfactory. | I44: 0 | J44: 7.6.1
A45: Ola | B45: 46313.292 | C45: 1 | D45: Fare shown vs fare charged | E45: fare_mismatch | F45: neg | G45: Driver asked for more than the app fare | H45: Worst experience with Ola... The vehicle got a breakdown in the middle and the driver stopped another auto by taking full money from my family and they(drivers without telling my family) made a deal to give extra 200 in the destination. We already agreed for extra money with the initial driver, he took that money and he made us to give another 200 to the new auto driver. !!!!! Regarding this issue,I wasn't able to speak with customer service since this OLA has no customer support !!!!! | I45: 0 | J45: 7.6.1
A46: Ola | B46: 46313.29 | C46: 1 | D46: Vague or other complaint | E46: other_complaint | F46: neg | H46: bad service | I46: 0 | J46: 7.6.1
A47: Ola | B47: 46313.228 | C47: 1 | D47: Cash vs UPI, payments, refunds | E47: payment_dispute | F47: neg | H47: I booked an ola outstation cab, I did the payment to the ola driver but the app is still asking me to pay some amount. There is no proper call support for this app. i sent a mail for [upi/email] they raised a ticket, which said ola money handles only transactions. From the app there is no way to reach your customer care. These ola computer calls are calling me continuously to pay the amount but i already paid it. Chat with ola support doesn't work only, why is it not fixed? . very bad supp | I47: 0 | J47: 7.6.1
A48: Ola | B48: 46313.177 | C48: 2 | D48: Driver cancels or refuses after accepting | E48: driver_cancel | F48: neg | H48: ola ki service achi nhi hai driver ride accept krne k baad aate nhi hai or Aaj tk kabhi customer care se baat bhi nhi Hui customer support accha nhi hai. | I48: 0 | J48: 7.5.9
A49: Ola | B49: 46313.168 | C49: 5 | D49: Praise: general | E49: praise_general | F49: pos | H49: "Most Excellent App By Ola". | I49: 1 | J49: 7.6.1
A50: Ola | B50: 46313.162 | C50: 5 | D50: Praise: general | E50: praise_general | F50: pos | H50: nice trip | I50: 0 | J50: 7.5.9
A51: Ola | B51: 46313.135 | C51: 1 | D51: Rude driver or vehicle condition | E51: driver_behaviour | F51: neg | H51: Extremely bad experience! The driver intentionally took a much longer route, wasting my time for no reason. Ola drivers have become highly unprofessional and unreliable. Rapido is way better than Ola now—their drivers stick to the right route and provide much better service. Disappointing from Ola! ⭐ | I51: 0
A52: Ola | B52: 46313.122 | C52: 1 | D52: App bugs, login, maps | E52: app_bugs | F52: neg | H52: The new update is ridiculous, not at all user friendly. And please update the map as much as possible with developing areas, accurate building names, etc. It's just huge inconvenience. And I use the app daily to travel between my house and office. And today I felt the ridicule of this app. so frustrating. | I52: 0 | J52: 7.5.9
A53: Ola | B53: 46313.116 | C53: 5 | D53: Praise: general | E53: praise_general | F53: pos | H53: good | I53: 0 | J53: 7.5.6
A54: Ola | B54: 46312.966 | C54: 5 | D54: Praise: general | E54: praise_general | F54: pos | H54: good so far | I54: 0 | J54: 7.5.3
A55: Ola | B55: 46312.855 | C55: 1 | D55: No cab/auto/bike available | E55: availability | F55: neg | H55: ola your rental services are very bad.... I scheduled a cab on rental to go the airport... And you didn't accept and didn't show me the reason why you declined. Horrible experience.. I never use this app. | I55: 0 | J55: 7.6.1
A56: Ola | B56: 46312.78 | C56: 5 | D56: Praise: general | E56: praise_general | F56: pos | H56: I think Ola riders are know giving quality, promptness, | I56: 0 | J56: 7.5.9
A57: Ola | B57: 46312.77 | C57: 3 | D57: Praise: general | E57: praise_general | F57: pos | H57: good | I57: 0 | J57: 7.6.1
A58: Ola | B58: 46312.733 | C58: 2 | D58: Prices too high | E58: high_prices | F58: neg | H58: Most Expensive | I58: 0 | J58: 7.5.9
A59: Ola | B59: 46312.729 | C59: 1 | D59: Vague or other complaint | E59: other_complaint | F59: neg | H59: Bad service | I59: 0 | J59: 7.6.1
A60: Ola | B60: 46312.725 | C60: 5 | D60: Praise: general | E60: praise_general | F60: pos | H60: all good | I60: 0 | J60: 7.5.9
A61: Ola | B61: 46312.674 | C61: 1 | D61: Fare shown vs fare charged | E61: fare_mismatch | F61: neg | G61: Driver asked for more than the app fare | H61: No customer support... No ans on ticket raised... Driver charging extra as they know that Ola doesn't take action... Pathetic | I61: 0
A62: Ola | B62: 46312.668 | C62: 1 | D62: Vague or other complaint | E62: other_complaint | F62: neg | H62: worst app | I62: 0 | J62: 7.5.9
A63: Ola | B63: 46312.626 | C63: 1 | D63: Support unreachable | E63: support | F63: neg | H63: there is no option for proper support. looting people | I63: 0 | J63: 7.5.9
A64: Ola | B64: 46312.615 | C64: 1 | D64: Fare shown vs fare charged | E64: fare_mismatch | F64: neg | G64: Driver asked for more than the app fare | H64: Pathetic Service and Extremely Unprofessional! Ola provide extremely disappointing service. They confirm bookings at a particular fare, but once the customer is waiting for the ride, drivers demand extra money to complete the trip. If customers refuse to pay these unreasonable additional charges, drivers often refuse to provide the service despite the confirmed booking. What is the point of booking a cab through an app if customers are forced to negotiate with drivers after the booking. | I64: 0 | J64: 7.6.1
A65: Ola | B65: 46312.604 | C65: 5 | D65: Praise: general | E65: praise_general | F65: pos | H65: ok | I65: 0 | J65: 7.6.1
A66: Ola | B66: 46312.594 | C66: 1 | D66: Unclear or off-topic | E66: unclear | F66: neg | H66: very very bad 🐷🐷🐷🐷 ola app | I66: 0
A67: Ola | B67: 46312.58 | C67: 5 | D67: Praise: general | E67: praise_general | F67: pos | H67: good | I67: 0 | J67: 7.6.1
A68: Ola | B68: 46312.577 | C68: 5 | D68: Praise: driver | E68: praise_driver | F68: pos | H68: good Driver | I68: 0 | J68: 7.5.9
A69: Ola | B69: 46312.546 | C69: 1 | D69: Prices too high | E69: high_prices | F69: neg | H69: no.1 chor ola is.. its price is always high & it has worst drivers & worst service.. | I69: 0
A70: Ola | B70: 46312.538 | C70: 1 | D70: Driver cancels or refuses after accepting | E70: driver_cancel | F70: neg | H70: bohot hi bekar app hai isme aj tak meri koi ride accept nhi hui hai to koi use mt kro isko | I70: 0
A71: Ola | B71: 46312.509 | C71: 1 | D71: Support unreachable | E71: support | F71: neg | H71: I’ve had a terrible experience with Ola because they add unnecessary cancellation fees—even when it’s the driver who cancels—and their customer support is absolutely pathetic. | I71: 0 | J71: 7.5.8
A72: Ola | B72: 46312.5 | C72: 1 | D72: App bugs, login, maps | E72: app_bugs | F72: neg | H72: kyc not happening hence I cant use get help option for my rides | I72: 1
A73: Ola | B73: 46312.49 | C73: 5 | D73: Praise: general | E73: praise_general | F73: pos | H73: very good | I73: 0 | J73: 7.5.9
A74: Ola | B74: 46312.48 | C74: 1 | D74: App bugs, login, maps | E74: app_bugs | F74: neg | H74: Be careful with this app, it accesses everything from your phone without asking for your permission. When I installed the app I received OTP through WhatsApp, it directly fetched the OTP. | I74: 0 | J74: 7.5.3
A75: Ola | B75: 46312.453 | C75: 3 | D75: Long wait after booking | E75: wait_time | F75: neg | H75: sometimes the waiting time is too long.It very difficult during emergency times. Kindly reduce the wait time. | I75: 0 | J75: 7.6.1
A76: Ola | B76: 46312.433 | C76: 1 | D76: Driver cancels or refuses after accepting | E76: driver_cancel | F76: neg | H76: It is very disgusting, drive demand for extra money furthermore the cancelled ride by themselves , if u have very urgent work and rely on the drive u're definitely going to miss that work just because of the extra power of cancellations given to the driver 😳 | I76: 0
A77: Ola | B77: 46312.394 | C77: 1 | D77: No cab/auto/bike available | E77: availability | F77: neg | H77: worst app ever when i need transport urgent it shows wait 2-3min and then it shows no rides available and asking more money for auto ride i will never use this app in my whole life | I77: 0
A78: Ola | B78: 46312.391 | C78: 1 | D78: Rude driver or vehicle condition | E78: driver_behaviour | F78: neg | H78: worst experience , drivers very worst | I78: 0 | J78: 7.6.1
A79: Ola | B79: 46312.389 | C79: 5 | D79: Praise: general | E79: praise_general | F79: pos | H79: This time having great experience 😌 with Ola ride | I79: 0 | J79: 7.6.1
A80: Ola | B80: 46312.362 | C80: 3 | D80: Vague or other complaint | E80: other_complaint | F80: neg | H80: some time this app is nightmare | I80: 0 | J80: 7.5.9
A81: Ola | B81: 46312.307 | C81: 5 | D81: Praise: general | E81: praise_general | F81: pos | H81: tik hi | I81: 1 | J81: 7.5.9
A82: Ola | B82: 46312.285 | C82: 1 | D82: No cab/auto/bike available | E82: availability | F82: neg | H82: very much disgusting app when needed no rides are available don't use this app | I82: 0 | J82: 7.5.9
A83: Ola | B83: 46312.272 | C83: 5 | D83: Praise: general | E83: praise_general | F83: pos | H83: good | I83: 0
A84: Ola | B84: 46312.238 | C84: 5 | D84: Praise: general | E84: praise_general | F84: pos | H84: Good | I84: 0 | J84: 7.6.1
A85: Ola | B85: 46312.175 | C85: 5 | D85: Praise: general | E85: praise_general | F85: pos | H85: excellent | I85: 0 | J85: 7.5.9
A86: Ola | B86: 46312.093 | C86: 1 | D86: Fare shown vs fare charged | E86: fare_mismatch | F86: neg | G86: In-app final fare higher than quoted | H86: third class and fraud app, I booked a ride at 230 and the fare automatically increased to 430... like seriously 😒 do you think this is fare? great whatever several apps are available I have uninstalled this pathetic app. DO NOT USE OLA | I86: 0 | J86: 7.5.9
A87: Ola | B87: 46312.074 | C87: 5 | D87: Praise: general | E87: praise_general | F87: pos | H87: Ola better than other ride app | I87: 0 | J87: 7.6.1
A88: Ola | B88: 46312.062 | C88: 5 | D88: Praise: general | E88: praise_general | F88: pos | H88: bes | I88: 0 | J88: 7.6.1
A89: Ola | B89: 46312.056 | C89: 1 | D89: Support unreachable | E89: support | F89: neg | H89: there is no direct support chat or call if anything happens no one will respond I had reported an issue where the ride was booked for female passenger where the total ride distance was 10.1km but he stopped the ride after going approximately 2.3km and took 557rs for it and he has abused with bad words on questioning for early drop he also said go and complaint to support he won't care and even after sending email to support and grievance there is no reply apart from automated 1st response. | I89: 0 | J89: 7.5.9
A90: Ola | B90: 46312.045 | C90: 1 | D90: Prices too high | E90: high_prices | F90: neg | H90: rate of traveling is high (Rs 300 it increases to Rs 500 , not ladies friendly | I90: 0 | J90: 7.6.1
A91: Ola | B91: 46312.041 | C91: 1 | D91: Unclear or off-topic | E91: unclear | F91: neg | H91: bad bad bad bad | I91: 0
A92: Ola | B92: 46312.04 | C92: 1 | D92: Support unreachable | E92: support | F92: neg | H92: I will definitely make sure as many customers as possible uninstall the Ola app. What kind of pathetic customer service is this? They just hang up the phone the moment you ask a question. And they’ve even blocked me from calling customer care—it’s an absolutely terrible app. Does anyone know how to file a case against the Ola app in the consumer court? Please let me know. | I92: 0
A93: Ola | B93: 46311.915 | C93: 5 | D93: Praise: general | E93: praise_general | F93: pos | H93: very good service | I93: 0 | J93: 7.5.9
A94: Ola | B94: 46311.829 | C94: 5 | D94: Praise: general | E94: praise_general | F94: pos | H94: verry nice | I94: 0 | J94: 7.6.1
A95: Ola | B95: 46311.815 | C95: 5 | D95: Praise: general | E95: praise_general | F95: pos | H95: good service | I95: 0 | J95: 7.5.9
A96: Ola | B96: 46311.808 | C96: 5 | D96: Praise: general | E96: praise_general | F96: pos | H96: good | I96: 0 | J96: 7.5.9
A97: Ola | B97: 46311.709 | C97: 2 | D97: Long wait after booking | E97: wait_time | F97: neg | H97: Too much time is taking the process. Always wait for the price increase. | I97: 0 | J97: 7.6.1
A98: Ola | B98: 46311.676 | C98: 4 | D98: Long wait after booking | E98: wait_time | F98: neg | H98: average but finding driver is taking to much time . time is wasting to much for waiting . not connecting immediately | I98: 0 | J98: 7.5.9
A99: Ola | B99: 46311.671 | C99: 5 | D99: Praise: general | E99: praise_general | F99: pos | H99: The ride was amazing and good music was played all during the ride.Thanks | I99: 0 | J99: 7.4.9
A100: Ola | B100: 46311.65 | C100: 1 | D100: Vague or other complaint | E100: other_complaint | F100: neg | H100: 3rd class service | I100: 0
...
